<?xml version="1.0" encoding="windows-1252" ?>
<!DOCTYPE Entity SYSTEM "jbo_03_01.dtd">
<!---->
<Entity
  xmlns="http://xmlns.oracle.com/bc4j"
  Name="AllCompany"
  Version="12.1.3.10.47"
  InheritPersonalization="merge"
  DBObjectType="table"
  DBObjectName="ALL_COMPANY"
  AliasName="AllCompany"
  BindingStyle="OracleName">
  <Attribute
    Name="Companyid"
    IsNotNull="true"
    Precision="15"
    ColumnName="COMPANYID"
    SQLType="VARCHAR"
    Type="java.lang.String"
    ColumnType="VARCHAR2"
    TableName="ALL_COMPANY"
    PrimaryKey="true">
    <DesignTime>
      <Attr Name="_DisplaySize" Value="15"/>
    </DesignTime>
  </Attribute>
  <Attribute
    Name="CompanyName"
    Precision="50"
    ColumnName="COMPANY_NAME"
    SQLType="VARCHAR"
    Type="java.lang.String"
    ColumnType="VARCHAR2"
    TableName="ALL_COMPANY">
    <DesignTime>
      <Attr Name="_DisplaySize" Value="50"/>
    </DesignTime>
  </Attribute>
  <Attribute
    Name="CompanyAddress"
    Precision="100"
    ColumnName="COMPANY_ADDRESS"
    SQLType="VARCHAR"
    Type="java.lang.String"
    ColumnType="VARCHAR2"
    TableName="ALL_COMPANY">
    <DesignTime>
      <Attr Name="_DisplaySize" Value="100"/>
    </DesignTime>
  </Attribute>
  <Attribute
    Name="CompanyShortName"
    Precision="20"
    ColumnName="COMPANY_SHORT_NAME"
    SQLType="VARCHAR"
    Type="java.lang.String"
    ColumnType="VARCHAR2"
    TableName="ALL_COMPANY">
    <DesignTime>
      <Attr Name="_DisplaySize" Value="20"/>
    </DesignTime>
  </Attribute>
  <Attribute
    Name="CreatedBy"
    Precision="20"
    ColumnName="CREATED_BY"
    SQLType="VARCHAR"
    Type="java.lang.String"
    ColumnType="VARCHAR2"
    TableName="ALL_COMPANY">
    <DesignTime>
      <Attr Name="_DisplaySize" Value="20"/>
    </DesignTime>
  </Attribute>
  <Attribute
    Name="ParentCompany"
    Precision="15"
    ColumnName="PARENT_COMPANY"
    SQLType="VARCHAR"
    Type="java.lang.String"
    ColumnType="VARCHAR2"
    TableName="ALL_COMPANY">
    <DesignTime>
      <Attr Name="_DisplaySize" Value="15"/>
    </DesignTime>
  </Attribute>
  <Attribute
    Name="CreatedDate"
    ColumnName="CREATED_DATE"
    SQLType="DATE"
    Type="java.sql.Timestamp"
    ColumnType="DATE"
    TableName="ALL_COMPANY"/>
  <Attribute
    Name="ModifiedBy"
    Precision="20"
    ColumnName="MODIFIED_BY"
    SQLType="VARCHAR"
    Type="java.lang.String"
    ColumnType="VARCHAR2"
    TableName="ALL_COMPANY">
    <DesignTime>
      <Attr Name="_DisplaySize" Value="20"/>
    </DesignTime>
  </Attribute>
  <Attribute
    Name="ModificationDate"
    ColumnName="MODIFICATION_DATE"
    SQLType="DATE"
    Type="java.sql.Timestamp"
    ColumnType="DATE"
    TableName="ALL_COMPANY"/>
  <Attribute
    Name="Active"
    Precision="1"
    ColumnName="ACTIVE"
    SQLType="VARCHAR"
    Type="java.lang.String"
    ColumnType="VARCHAR2"
    TableName="ALL_COMPANY">
    <DesignTime>
      <Attr Name="_DisplaySize" Value="1"/>
    </DesignTime>
  </Attribute>
  <Attribute
    Name="TelNo"
    Precision="60"
    ColumnName="TEL_NO"
    SQLType="VARCHAR"
    Type="java.lang.String"
    ColumnType="VARCHAR2"
    TableName="ALL_COMPANY">
    <DesignTime>
      <Attr Name="_DisplaySize" Value="60"/>
    </DesignTime>
  </Attribute>
  <Attribute
    Name="MobileNo"
    Precision="20"
    ColumnName="MOBILE_NO"
    SQLType="VARCHAR"
    Type="java.lang.String"
    ColumnType="VARCHAR2"
    TableName="ALL_COMPANY">
    <DesignTime>
      <Attr Name="_DisplaySize" Value="20"/>
    </DesignTime>
  </Attribute>
  <Attribute
    Name="Email"
    Precision="50"
    ColumnName="EMAIL"
    SQLType="VARCHAR"
    Type="java.lang.String"
    ColumnType="VARCHAR2"
    TableName="ALL_COMPANY">
    <DesignTime>
      <Attr Name="_DisplaySize" Value="50"/>
    </DesignTime>
  </Attribute>
  <Attribute
    Name="FaxNo"
    Precision="20"
    ColumnName="FAX_NO"
    SQLType="VARCHAR"
    Type="java.lang.String"
    ColumnType="VARCHAR2"
    TableName="ALL_COMPANY">
    <DesignTime>
      <Attr Name="_DisplaySize" Value="20"/>
    </DesignTime>
  </Attribute>
  <Attribute
    Name="Country"
    Precision="50"
    ColumnName="COUNTRY"
    SQLType="VARCHAR"
    Type="java.lang.String"
    ColumnType="VARCHAR2"
    TableName="ALL_COMPANY">
    <DesignTime>
      <Attr Name="_DisplaySize" Value="50"/>
    </DesignTime>
  </Attribute>
  <Attribute
    Name="City"
    Precision="50"
    ColumnName="CITY"
    SQLType="VARCHAR"
    Type="java.lang.String"
    ColumnType="VARCHAR2"
    TableName="ALL_COMPANY">
    <DesignTime>
      <Attr Name="_DisplaySize" Value="50"/>
    </DesignTime>
  </Attribute>
  <Attribute
    Name="RegNo"
    Precision="50"
    ColumnName="REG_NO"
    SQLType="VARCHAR"
    Type="java.lang.String"
    ColumnType="VARCHAR2"
    TableName="ALL_COMPANY">
    <DesignTime>
      <Attr Name="_DisplaySize" Value="50"/>
    </DesignTime>
  </Attribute>
  <Attribute
    Name="NtnNo"
    Precision="50"
    ColumnName="NTN_NO"
    SQLType="VARCHAR"
    Type="java.lang.String"
    ColumnType="VARCHAR2"
    TableName="ALL_COMPANY">
    <DesignTime>
      <Attr Name="_DisplaySize" Value="50"/>
    </DesignTime>
  </Attribute>
  <Attribute
    Name="StaxNo"
    Precision="50"
    ColumnName="STAX_NO"
    SQLType="VARCHAR"
    Type="java.lang.String"
    ColumnType="VARCHAR2"
    TableName="ALL_COMPANY">
    <DesignTime>
      <Attr Name="_DisplaySize" Value="50"/>
    </DesignTime>
  </Attribute>
  <Attribute
    Name="CompanyAddressUr"
    Precision="100"
    ColumnName="COMPANY_ADDRESS_UR"
    SQLType="VARCHAR"
    Type="java.lang.String"
    ColumnType="VARCHAR2"
    TableName="ALL_COMPANY">
    <DesignTime>
      <Attr Name="_DisplaySize" Value="100"/>
    </DesignTime>
  </Attribute>
  <Attribute
    Name="CompanyCode"
    Precision="15"
    ColumnName="COMPANY_CODE"
    SQLType="VARCHAR"
    Type="java.lang.String"
    ColumnType="VARCHAR2"
    TableName="ALL_COMPANY">
    <DesignTime>
      <Attr Name="_DisplaySize" Value="15"/>
    </DesignTime>
  </Attribute>
  <AccessorAttribute
    Name="AllCompany"
    Association="erpsolscm.erpsolscmmodel.erpsolscmeo.R263Assoc"
    AssociationEnd="erpsolscm.erpsolscmmodel.erpsolscmeo.R263Assoc.AllCompany"
    AssociationOtherEnd="erpsolscm.erpsolscmmodel.erpsolscmeo.R263Assoc.ParentCompanyAllCompany"
    Type="oracle.jbo.RowIterator"
    IsUpdateable="false"/>
  <AccessorAttribute
    Name="ParentCompanyAllCompany"
    Association="erpsolscm.erpsolscmmodel.erpsolscmeo.R263Assoc"
    AssociationEnd="erpsolscm.erpsolscmmodel.erpsolscmeo.R263Assoc.ParentCompanyAllCompany"
    AssociationOtherEnd="erpsolscm.erpsolscmmodel.erpsolscmeo.R263Assoc.AllCompany"
    Type="oracle.jbo.server.EntityImpl"
    IsUpdateable="true"/>
  <Key
    Name="XpkallCompany"
    PrimaryKey="true">
    <DesignTime>
      <Attr Name="_DBObjectName" Value="XPKALL_COMPANY"/>
    </DesignTime>
    <AttrArray Name="Attributes">
      <Item Value="erpsolscm.erpsolscmmodel.erpsolscmeo.AllCompany.Companyid"/>
    </AttrArray>
  </Key>
  <Key
    Name="R263">
    <DesignTime>
      <Attr Name="_referencedKey" Value="XPKALL_COMPANY"/>
      <Attr Name="_isForeign" Value="true"/>
      <Attr Name="_DBObjectName" Value="R_263"/>
    </DesignTime>
    <AttrArray Name="Attributes">
      <Item Value="erpsolscm.erpsolscmmodel.erpsolscmeo.AllCompany.ParentCompany"/>
    </AttrArray>
  </Key>
</Entity>
